CHANGES.txt
LICENSE.txt
MANIFEST.in
README.rst
setup.cfg
setup.py
wsgitest/__init__.py
wsgitest/server.py
wsgitest/utils.py
wsgitest.egg-info/PKG-INFO
wsgitest.egg-info/SOURCES.txt
wsgitest.egg-info/dependency_links.txt
wsgitest.egg-info/requires.txt
wsgitest.egg-info/top_level.txt