Metadata-Version: 1.1
Name: wsgitest
Version: 0.1.0
Summary: Standalone WSGI server for running tests purpose.
Home-page: http://github.com/osantana/wsgitest
Author: Osvaldo Santana Neto
Author-email: wsgitest@osantana.me
License: MIT
Download-URL: https://github.com/osantana/wsgitest/tarball/0.1.0
Keywords: testing test server
Platform: any
Classifier: Development Status :: 3 - Alpha
Classifier: Intended Audience :: Developers
Classifier: License :: OSI Approved :: MIT License
Classifier: Natural Language :: English
Classifier: Operating System :: OS Independent
Classifier: Topic :: Software Development :: Libraries
Classifier: Topic :: Software Development :: Testing
Classifier: Programming Language :: Python
Classifier: Programming Language :: Python :: 2
Classifier: Programming Language :: Python :: 2.7
Classifier: Programming Language :: Python :: 3
Classifier: Programming Language :: Python :: 3.4
